topological_clustering/__init__.py
topological_clustering/tomato.py
topological_clustering/tomato_utils.py
topological_clustering/tomato_warnings.py
topological_clustering-0.1.0.dist-info/DESCRIPTION.rst
topological_clustering-0.1.0.dist-info/METADATA
topological_clustering-0.1.0.dist-info/RECORD
topological_clustering-0.1.0.dist-info/WHEEL
topological_clustering-0.1.0.dist-info/metadata.json
topological_clustering-0.1.0.dist-info/top_level.txt
